README.md
credstash.py
setup.cfg
setup.py
credstash_any_crypto.egg-info/PKG-INFO
credstash_any_crypto.egg-info/SOURCES.txt
credstash_any_crypto.egg-info/dependency_links.txt
credstash_any_crypto.egg-info/entry_points.txt
credstash_any_crypto.egg-info/requires.txt
credstash_any_crypto.egg-info/top_level.txt