Metadata-Version: 1.1
Name: credstash-any-crypto
Version: 1.14.1
Summary: A utility for managing secrets in the cloud using AWS KMS and DynamoDB
Home-page: https://github.com/globality-corp/credstash
Author: UNKNOWN
Author-email: UNKNOWN
License: Apache2
Platform: UNKNOWN
Classifier: Intended Audience :: Developers
Classifier: Intended Audience :: System Administrators
Classifier: License :: OSI Approved :: Apache Software License
